castpfoldpy/__init__.py
castpfoldpy/cli.py
castpfoldpy/client.py
castpfoldpy-0.1.2.dist-info/licenses/LICENSE
castpfoldpy-0.1.2.dist-info/WHEEL
castpfoldpy-0.1.2.dist-info/entry_points.txt
castpfoldpy-0.1.2.dist-info/METADATA
castpfoldpy-0.1.2.dist-info/RECORD
