Metadata-Version: 2.4
Name: castpfoldpy
Version: 0.1.2
Summary: A Python CLI program to run [CASTpFold](https://cfold.bme.uic.edu/castpfold/) code from the command line
Author-email: athul111@gmail.com
License-Expression: GPL-3.0-or-later
License-File: LICENSE
Classifier: Programming Language :: Python :: 3.10
Classifier: Programming Language :: Python :: 3.11
Classifier: Programming Language :: Python :: 3.12
Classifier: Programming Language :: Python :: 3.13
Classifier: Operating System :: OS Independent
Requires-Dist: biopython>=1.85
Requires-Dist: dataclasses>=0.6
Requires-Dist: pandas>=2.3.3
Requires-Dist: requests>=2.32.5
Requires-Dist: tqdm>=4.67.1
Requires-Python: >=3.10
Project-URL: Homepage, https://github.com/athulvis/castp-Script
Project-URL: Issues, https://github.com/athulvis/castp-Script/issues
